Metadata-Version: 2.1
Name: dafne-models-torch_models
Version: 2.0a4
Summary: Deep Learning models module for Dafne
Home-page: https://github.com/dafne-imaging/dafne-models
Author: Francesco Santini
Author-email: francesco.santini@unibas.ch
Project-URL: Bug Tracker, https://github.com/dafne-imaging/dafne-model/issues
Classifier: Programming Language :: Python :: 3
Classifier: License :: OSI Approved :: GNU General Public License v3 or later (GPLv3+)
Classifier: Operating System :: OS Independent
Requires-Python: >=3.6
License-File: LICENSE
Requires-Dist: matplotlib
Requires-Dist: ormir-pyvoxel
Requires-Dist: dafne-dicomUtils >=0.1.7
Requires-Dist: dill
Requires-Dist: dafne-dl-torch-models >=2.0a2
Provides-Extra: gui
Requires-Dist: PyQt5 ; extra == 'gui'
